gimp/__init__.py
gimp/pdb.py
gimp/__pycache__/__init__.cpython-36.pyc
gimpenums/__init__.py
gimpenums/__pycache__/__init__.cpython-36.pyc
gimpfu/__init__.py
pgimp/GimpException.py
pgimp/GimpFile.py
pgimp/GimpFileCollection.py
pgimp/GimpFileCollectionTest.py
pgimp/GimpFileTest.py
pgimp/GimpScriptRunner.py
pgimp/GimpScriptRunnerTest.py
pgimp/__init__.py
pgimp/doc/GimpDocumentationGenerator.py
pgimp/doc/GimpDocumentationGeneratorTest.py
pgimp/doc/__init__.py
pgimp/doc/output/Output.py
pgimp/doc/output/OutputPythonSkeleton.py
pgimp/doc/output/__init__.py
pgimp/gimp/__init__.py
pgimp/gimp/colormap.py
pgimp/gimp/file.py
pgimp/gimp/image.py
pgimp/gimp/initializer.py
pgimp/gimp/layer.py
pgimp/gimp/parameter.py
pgimp/gimp/parameter_Test.py
pgimp/layers/Layer.py
pgimp/layers/__init__.py
pgimp/util/TempFile.py
pgimp/util/TempFileTest.py
pgimp/util/__init__.py
pgimp/util/file.py
pgimp/util/file_Test.py
pgimp/util/string.py
pgimp/util/string_Test.py
pgimp-1.0.0a2.dist-info/LICENSE
pgimp-1.0.0a2.dist-info/METADATA
pgimp-1.0.0a2.dist-info/WHEEL
pgimp-1.0.0a2.dist-info/top_level.txt
pgimp-1.0.0a2.dist-info/RECORD
