Metadata-Version: 2.1
Name: pgimp
Version: 1.0.0a2
Summary: Interacting with gimp in python3.
Home-page: https://github.com/mabu-github/pgimp
Author: Mathias Burger
Author-email: mathias.burger@gmail.com
License: MIT
Keywords: pgimp,gimp,annotating,annotation,machine-learning,graphics
Platform: UNKNOWN
Classifier: Programming Language :: Python :: 3.6
Classifier: License :: OSI Approved :: MIT License
Classifier: Operating System :: POSIX :: Linux
Classifier: Operating System :: MacOS
Classifier: Topic :: Multimedia :: Graphics
Classifier: Topic :: Scientific/Engineering :: Artificial Intelligence
Requires-Dist: numpy (>=1.10)
Requires-Dist: psutil
